webtk/__init__.py
webtk/binder.py
webtk/chrome.py
webtk/edge.py
webtk/server.py
webtk/utils.py
webtk/webview.py
pwebtk-0.0.1.dist-info/LICENSE.md
pwebtk-0.0.1.dist-info/METADATA
pwebtk-0.0.1.dist-info/WHEEL
pwebtk-0.0.1.dist-info/top_level.txt
pwebtk-0.0.1.dist-info/zip-safe
pwebtk-0.0.1.dist-info/RECORD
